rez/__init__.py
rez/__main__.py
rez/build_process_.py
rez/build_system.py
rez/config.py
rez/developer_package.py
rez/exceptions.py
rez/package_bind.py
rez/package_copy.py
rez/package_filter.py
rez/package_help.py
rez/package_maker__.py
rez/package_order.py
rez/package_py_utils.py
rez/package_repository.py
rez/package_resources_.py
rez/package_search.py
rez/package_serialise.py
rez/package_test.py
rez/packages_.py
rez/pip.py
rez/plugin_managers.py
rez/release_hook.py
rez/release_vcs.py
rez/resolved_context.py
rez/resolver.py
rez/rex.py
rez/rex_bindings.py
rez/rezconfig.py
rez/serialise.py
rez/shells.py
rez/solver.py
rez/status.py
rez/suite.py
rez/system.py
rez/util.py
rez/wrapper.py
rez/backport/__init__.py
rez/backport/importlib.py
rez/backport/lru_cache.py
rez/backport/ordereddict.py
rez/backport/shutilwhich.py
rez/backport/zipfile.py
rez/bind/PyQt.py
rez/bind/PySide.py
rez/bind/__init__.py
rez/bind/_pymodule.py
rez/bind/_utils.py
rez/bind/arch.py
rez/bind/bleeding_rez.py
rez/bind/cmake.py
rez/bind/hello_world.py
rez/bind/os.py
rez/bind/platform.py
rez/bind/python.py
rez/bind/rez.py
rez/bind/rezgui.py
rez/bind/sip.py
rez/cli/__init__.py
rez/cli/_bez.py
rez/cli/_complete_util.py
rez/cli/_main.py
rez/cli/_util.py
rez/cli/bind.py
rez/cli/build.py
rez/cli/complete.py
rez/cli/config.py
rez/cli/context.py
rez/cli/cp.py
rez/cli/depends.py
rez/cli/diff.py
rez/cli/env.py
rez/cli/forward.py
rez/cli/gui.py
rez/cli/help.py
rez/cli/interpret.py
rez/cli/memcache.py
rez/cli/pip.py
rez/cli/plugins.py
rez/cli/python.py
rez/cli/release.py
rez/cli/search.py
rez/cli/selftest.py
rez/cli/status.py
rez/cli/suite.py
rez/cli/test.py
rez/cli/view.py
rez/cli/yaml2py.py
rez/completion/complete.csh
rez/completion/complete.sh
rez/tests/README
rez/tests/__init__.py
rez/tests/test_build.py
rez/tests/test_commands.py
rez/tests/test_completion.py
rez/tests/test_config.py
rez/tests/test_context.py
rez/tests/test_copy_package.py
rez/tests/test_formatter.py
rez/tests/test_imports.py
bleeding_rez-2.40.5.dist-info/COPYING.LESSER
bleeding_rez-2.40.5.dist-info/METADATA
bleeding_rez-2.40.5.dist-info/WHEEL
bleeding_rez-2.40.5.dist-info/entry_points.txt
bleeding_rez-2.40.5.dist-info/top_level.txt
bleeding_rez-2.40.5.dist-info/RECORD
