Metadata-Version: 2.1
Name: bleeding-rez
Version: 2.40.5
Summary: A cross-platform packaging system that can build and install multiple version of packages, and dynamically configure resolved environments at runtime.
Home-page: https://github.com/mottosso/bleeding-rez
Author: Marcus Ottosson
Author-email: konstruktion@gmail.com
License: LGPL
Keywords: package resolve version build install software management
Platform: UNKNOWN
Classifier: Development Status :: 5 - Production/Stable
Classifier: License :: OSI Approved :: GNU Lesser General Public License v3 (LGPLv3)
Classifier: Intended Audience :: Developers
Classifier: Operating System :: OS Independent
Classifier: Programming Language :: Python
Classifier: Programming Language :: Python :: 2
Classifier: Programming Language :: Python :: 2.6
Classifier: Programming Language :: Python :: 2.7
Classifier: Programming Language :: Python :: 3
Classifier: Programming Language :: Python :: 3.6
Classifier: Programming Language :: Python :: 3.7
Classifier: Topic :: Software Development
Classifier: Topic :: System :: Software Distribution
